{".class": "MypyFile", "_fullname": "jobExample", "is_partial_stub_package": false, "is_stub": false, "names": {".class": "SymbolTable", "CronTab": {".class": "SymbolTableNode", "kind": "Gdef", "node": {".class": "Var", "flags": ["is_suppressed_import"], "fullname": "jobExample.CronTab", "name": "CronTab", "type": {".class": "AnyType", "missing_import_name": "jobExample.CronTab", "source_any": null, "type_of_any": 3}}}, "__doc__": {".class": "SymbolTableNode", "kind": "Gdef", "node": {".class": "Var", "flags": [], "fullname": "jobExample.__doc__", "name": "__doc__", "type": "builtins.str"}}, "__file__": {".class": "SymbolTableNode", "kind": "Gdef", "node": {".class": "Var", "flags": [], "fullname": "jobExample.__file__", "name": "__file__", "type": "builtins.str"}}, "__name__": {".class": "SymbolTableNode", "kind": "Gdef", "node": {".class": "Var", "flags": [], "fullname": "jobExample.__name__", "name": "__name__", "type": "builtins.str"}}, "__package__": {".class": "SymbolTableNode", "kind": "Gdef", "node": {".class": "Var", "flags": [], "fullname": "jobExample.__package__", "name": "__package__", "type": "builtins.str"}}, "sys": {".class": "SymbolTableNode", "cross_ref": "sys", "kind": "Gdef"}}, "path": "/Users/miroslavpolednak/Git/Python/pythonLern-1/jobExample.py"}